rootbox/__init__.py
rootbox/__main__.py
rootbox/colorhelper.py
rootbox/container.py
rootbox/enter.py
rootbox/http.py
rootbox/mount.py
rootbox/path.py
rootbox/process.py
rootbox/rootfs.py
rootbox/size.py
rootbox/socket.py
rootbox/unshare.py
rootbox/verbose.py
rootbox/version.py
rootbox/cli/cmd_exec.py
rootbox/cli/cmd_lxc.py
rootbox/cli/cmd_pull.py
rootbox/cli/cmd_run.py
rootbox/cli/cmd_start.py
rootbox/cli/main.py
rootbox/images/__init__.py
rootbox/images/cache.py
rootbox/images/handler.py
rootbox/images/http.py
rootbox/images/lxc.py
rootbox/images/pull.py
rootbox/images/tar.py
rootbox/images/url_parser.py
rootbox/shell/__init__.py
rootbox/shell/execute.py
rootbox/shell/systeminfo.py
tests/test_cmd_pull.py
tests/test_cmd_start.py
tests/test_image_handlers.py
tests/test_image_url.py
tests/test_lib_container.py
tests/test_manager.py
tests/test_pull.py
tests/test_rootfs.py
rootbox-0.0.12.dist-info/LICENSE
rootbox-0.0.12.dist-info/METADATA
rootbox-0.0.12.dist-info/WHEEL
rootbox-0.0.12.dist-info/entry_points.txt
rootbox-0.0.12.dist-info/top_level.txt
rootbox-0.0.12.dist-info/RECORD
