Metadata-Version: 2.1
Name: rootbox
Version: 0.0.12
Summary: Portable reproducible environments for Linux applications
Home-page: https://github.com/joaompinto/rootbox
Author: João Pinto
Author-email: lamego.pinto@gmail.com
License: MIT
Classifier: Development Status :: 4 - Beta
Classifier: Environment :: Console
Classifier: Intended Audience :: Developers
Classifier: License :: OSI Approved :: MIT License
Classifier: Operating System :: OS Independent
Classifier: Programming Language :: Python
Classifier: Programming Language :: Python :: 3.10
Classifier: Programming Language :: Python :: 3.11
Classifier: Programming Language :: Python :: 3 :: Only
Classifier: Topic :: Software Development :: Libraries :: Python Modules
License-File: LICENSE
Requires-Dist: print-err
Requires-Dist: requests
Requires-Dist: rich
Requires-Dist: termcolor
Requires-Dist: typer (>=0.9.0)
Requires-Dist: xdg
